[
    {
        "Name": "Sawsbuck",
        "Pokedex_Number": "586",
        "Generation": "5",
        "Evolution_Stage": "",
        "Evolved": "0",
        "FamilyID": "",
        "type_1": "normal",
        "type_2": "grass",
        "weather_1": "Partly cloudy",
        "weather_2": "Sunny/clear",
        "STAT_TOTAL": "504",
        "ATK": "198",
        "DEF": "146",
        "STA": "160",
        "Legendary": "0",
        "CP_MAX": "2233"
    },
    {
        "Name": "Emolga",
        "Pokedex_Number": "587",
        "Generation": "5",
        "Evolution_Stage": "",
        "Evolved": "0",
        "FamilyID": "",
        "type_1": "electric",
        "type_2": "flying",
        "weather_1": "Rainy",
        "weather_2": "Windy",
        "STAT_TOTAL": "395",
        "ATK": "158",
        "DEF": "127",
        "STA": "110",
        "Legendary": "0",
        "CP_MAX": "1439"
    },
    {
        "Name": "Karrablast",
        "Pokedex_Number": "588",
        "Generation": "5",
        "Evolution_Stage": "",
        "Evolved": "0",
        "FamilyID": "",
        "type_1": "bug",
        "type_2": "",
        "weather_1": "Rainy",
        "weather_2": "",
        "STAT_TOTAL": "324",
        "ATK": "137",
        "DEF": "87",
        "STA": "100",
        "Legendary": "0",
        "CP_MAX": "1028"
    },
    {
        "Name": "Escavalier",
        "Pokedex_Number": "589",
        "Generation": "5",
        "Evolution_Stage": "Evolved",
        "Evolved": "0",
        "FamilyID": "",
        "type_1": "bug",
        "type_2": "steel",
        "weather_1": "Rainy",
        "weather_2": "Snow",
        "STAT_TOTAL": "550",
        "ATK": "223",
        "DEF": "187",
        "STA": "140",
        "Legendary": "0",
        "CP_MAX": "2630"
    },
    {
        "Name": "Foongus",
        "Pokedex_Number": "590",
        "Generation": "5",
        "Evolution_Stage": "",
        "Evolved": "0",
        "FamilyID": "",
        "type_1": "grass",
        "type_2": "poison",
        "weather_1": "Sunny/clear",
        "weather_2": "Cloudy",
        "STAT_TOTAL": "330",
        "ATK": "97",
        "DEF": "95",
        "STA": "138",
        "Legendary": "0",
        "CP_MAX": "907"
    },
    {
        "Name": "Amoonguss",
        "Pokedex_Number": "591",
        "Generation": "5",
        "Evolution_Stage": "",
        "Evolved": "0",
        "FamilyID": "",
        "type_1": "grass",
        "type_2": "poison",
        "weather_1": "Sunny/clear",
        "weather_2": "Cloudy",
        "STAT_TOTAL": "527",
        "ATK": "155",
        "DEF": "144",
        "STA": "228",
        "Legendary": "0",
        "CP_MAX": "2087"
    },
    {
        "Name": "Frillish",
        "Pokedex_Number": "592",
        "Generation": "5",
        "Evolution_Stage": "",
        "Evolved": "0",
        "FamilyID": "",
        "type_1": "water",
        "type_2": "ghost",
        "weather_1": "Rainy",
        "weather_2": "Fog",
        "STAT_TOTAL": "375",
        "ATK": "115",
        "DEF": "150",
        "STA": "110",
        "Legendary": "0",
        "CP_MAX": "1166"
    },
    {
        "Name": "Jellicent",
        "Pokedex_Number": "593",
        "Generation": "5",
        "Evolution_Stage": "Evolved",
        "Evolved": "0",
        "FamilyID": "",
        "type_1": "water",
        "type_2": "ghost",
        "weather_1": "Rainy",
        "weather_2": "Fog",
        "STAT_TOTAL": "554",
        "ATK": "159",
        "DEF": "195",
        "STA": "200",
        "Legendary": "0",
        "CP_MAX": "2309"
    },
    {
        "Name": "Alomomola",
        "Pokedex_Number": "594",
        "Generation": "5",
        "Evolution_Stage": "Evolved",
        "Evolved": "0",
        "FamilyID": "",
        "type_1": "water",
        "type_2": "",
        "weather_1": "Rainy",
        "weather_2": "",
        "STAT_TOTAL": "616",
        "ATK": "138",
        "DEF": "148",
        "STA": "330",
        "Legendary": "0",
        "CP_MAX": "2266"
    },
    {
        "Name": "Joltik",
        "Pokedex_Number": "595",
        "Generation": "5",
        "Evolution_Stage": "",
        "Evolved": "0",
        "FamilyID": "",
        "type_1": "bug",
        "type_2": "electric",
        "weather_1": "Rainy",
        "weather_2": "",
        "STAT_TOTAL": "308",
        "ATK": "110",
        "DEF": "98",
        "STA": "100",
        "Legendary": "0",
        "CP_MAX": "889"
    },
    {
        "Name": "Galvantula",
        "Pokedex_Number": "596",
        "Generation": "5",
        "Evolution_Stage": "",
        "Evolved": "0",
        "FamilyID": "",
        "type_1": "bug",
        "type_2": "electric",
        "weather_1": "Rainy",
        "weather_2": "",
        "STAT_TOTAL": "469",
        "ATK": "201",
        "DEF": "128",
        "STA": "140",
        "Legendary": "0",
        "CP_MAX": "2008"
    },
    {
        "Name": "Ferroseed",
        "Pokedex_Number": "597",
        "Generation": "5",
        "Evolution_Stage": "",
        "Evolved": "0",
        "FamilyID": "",
        "type_1": "grass",
        "type_2": "steel",
        "weather_1": "Sunny/clear",
        "weather_2": "Snow",
        "STAT_TOTAL": "327",
        "ATK": "82",
        "DEF": "157",
        "STA": "88",
        "Legendary": "0",
        "CP_MAX": "806"
    },
    {
        "Name": "Ferrothorn",
        "Pokedex_Number": "598",
        "Generation": "5",
        "Evolution_Stage": "Evolved",
        "Evolved": "0",
        "FamilyID": "",
        "type_1": "grass",
        "type_2": "steel",
        "weather_1": "Sunny/clear",
        "weather_2": "Snow",
        "STAT_TOTAL": "536",
        "ATK": "158",
        "DEF": "230",
        "STA": "148",
        "Legendary": "0",
        "CP_MAX": "2159"
    },
    {
        "Name": "Klink",
        "Pokedex_Number": "599",
        "Generation": "5",
        "Evolution_Stage": "",
        "Evolved": "0",
        "FamilyID": "",
        "type_1": "steel",
        "type_2": "",
        "weather_1": "Snow",
        "weather_2": "",
        "STAT_TOTAL": "304",
        "ATK": "98",
        "DEF": "126",
        "STA": "80",
        "Legendary": "0",
        "CP_MAX": "816"
    },
    {
        "Name": "Klang",
        "Pokedex_Number": "600",
        "Generation": "5",
        "Evolution_Stage": "",
        "Evolved": "0",
        "FamilyID": "",
        "type_1": "steel",
        "type_2": "",
        "weather_1": "Snow",
        "weather_2": "",
        "STAT_TOTAL": "449",
        "ATK": "150",
        "DEF": "179",
        "STA": "120",
        "Legendary": "0",
        "CP_MAX": "1667"
    },
    {
        "Name": "Klinklang",
        "Pokedex_Number": "601",
        "Generation": "5",
        "Evolution_Stage": "Evolved",
        "Evolved": "0",
        "FamilyID": "",
        "type_1": "steel",
        "type_2": "",
        "weather_1": "Snow",
        "weather_2": "",
        "STAT_TOTAL": "549",
        "ATK": "199",
        "DEF": "230",
        "STA": "120",
        "Legendary": "0",
        "CP_MAX": "2430"
    },
    {
        "Name": "Tynamo",
        "Pokedex_Number": "602",
        "Generation": "5",
        "Evolution_Stage": "",
        "Evolved": "0",
        "FamilyID": "",
        "type_1": "electric",
        "type_2": "",
        "weather_1": "Rainy",
        "weather_2": "",
        "STAT_TOTAL": "253",
        "ATK": "105",
        "DEF": "78",
        "STA": "70",
        "Legendary": "0",
        "CP_MAX": "666"
    },
    {
        "Name": "Eelektrik",
        "Pokedex_Number": "603",
        "Generation": "5",
        "Evolution_Stage": "",
        "Evolved": "0",
        "FamilyID": "",
        "type_1": "electric",
        "type_2": "",
        "weather_1": "Rainy",
        "weather_2": "",
        "STAT_TOTAL": "416",
        "ATK": "156",
        "DEF": "130",
        "STA": "130",
        "Legendary": "0",
        "CP_MAX": "1548"
    },
    {
        "Name": "Eelektross",
        "Pokedex_Number": "604",
        "Generation": "5",
        "Evolution_Stage": "Lower",
        "Evolved": "0",
        "FamilyID": "",
        "type_1": "electric",
        "type_2": "",
        "weather_1": "Rainy",
        "weather_2": "",
        "STAT_TOTAL": "539",
        "ATK": "217",
        "DEF": "152",
        "STA": "170",
        "Legendary": "0",
        "CP_MAX": "2546"
    },
    {
        "Name": "Elgyem",
        "Pokedex_Number": "605",
        "Generation": "5",
        "Evolution_Stage": "",
        "Evolved": "0",
        "FamilyID": "",
        "type_1": "psychic",
        "type_2": "",
        "weather_1": "Windy",
        "weather_2": "",
        "STAT_TOTAL": "358",
        "ATK": "148",
        "DEF": "100",
        "STA": "110",
        "Legendary": "0",
        "CP_MAX": "1220"
    },
    {
        "Name": "Beheeyem",
        "Pokedex_Number": "606",
        "Generation": "5",
        "Evolution_Stage": "Evolved",
        "Evolved": "0",
        "FamilyID": "",
        "type_1": "psychic",
        "type_2": "",
        "weather_1": "Windy",
        "weather_2": "",
        "STAT_TOTAL": "543",
        "ATK": "221",
        "DEF": "172",
        "STA": "150",
        "Legendary": "0",
        "CP_MAX": "2589"
    },
    {
        "Name": "Litwick",
        "Pokedex_Number": "607",
        "Generation": "5",
        "Evolution_Stage": "",
        "Evolved": "0",
        "FamilyID": "",
        "type_1": "ghost",
        "type_2": "fire",
        "weather_1": "Fog",
        "weather_2": "Sunny/clear",
        "STAT_TOTAL": "306",
        "ATK": "108",
        "DEF": "98",
        "STA": "100",
        "Legendary": "0",
        "CP_MAX": "875"
    },
    {
        "Name": "Lampent",
        "Pokedex_Number": "608",
        "Generation": "5",
        "Evolution_Stage": "",
        "Evolved": "0",
        "FamilyID": "",
        "type_1": "ghost",
        "type_2": "fire",
        "weather_1": "Fog",
        "weather_2": "Sunny/clear",
        "STAT_TOTAL": "404",
        "ATK": "169",
        "DEF": "115",
        "STA": "120",
        "Legendary": "0",
        "CP_MAX": "1522"
    },
    {
        "Name": "Chandelure",
        "Pokedex_Number": "609",
        "Generation": "5",
        "Evolution_Stage": "Lower",
        "Evolved": "0",
        "FamilyID": "",
        "type_1": "ghost",
        "type_2": "fire",
        "weather_1": "Fog",
        "weather_2": "Sunny/clear",
        "STAT_TOTAL": "573",
        "ATK": "271",
        "DEF": "182",
        "STA": "120",
        "Legendary": "0",
        "CP_MAX": "2913"
    },
    {
        "Name": "Axew",
        "Pokedex_Number": "610",
        "Generation": "5",
        "Evolution_Stage": "",
        "Evolved": "0",
        "FamilyID": "",
        "type_1": "dragon",
        "type_2": "",
        "weather_1": "Windy",
        "weather_2": "",
        "STAT_TOTAL": "357",
        "ATK": "154",
        "DEF": "111",
        "STA": "92",
        "Legendary": "0",
        "CP_MAX": "1225"
    },
    {
        "Name": "Fraxure",
        "Pokedex_Number": "611",
        "Generation": "5",
        "Evolution_Stage": "",
        "Evolved": "0",
        "FamilyID": "",
        "type_1": "dragon",
        "type_2": "",
        "weather_1": "Windy",
        "weather_2": "",
        "STAT_TOTAL": "477",
        "ATK": "212",
        "DEF": "133",
        "STA": "132",
        "Legendary": "0",
        "CP_MAX": "2091"
    },
    {
        "Name": "Haxorus",
        "Pokedex_Number": "612",
        "Generation": "5",
        "Evolution_Stage": "Evolved",
        "Evolved": "0",
        "FamilyID": "",
        "type_1": "dragon",
        "type_2": "",
        "weather_1": "Windy",
        "weather_2": "",
        "STAT_TOTAL": "619",
        "ATK": "284",
        "DEF": "183",
        "STA": "152",
        "Legendary": "0",
        "CP_MAX": "3395"
    },
    {
        "Name": "Cubchoo",
        "Pokedex_Number": "613",
        "Generation": "5",
        "Evolution_Stage": "",
        "Evolved": "0",
        "FamilyID": "",
        "type_1": "ice",
        "type_2": "",
        "weather_1": "Snow",
        "weather_2": "",
        "STAT_TOTAL": "312",
        "ATK": "128",
        "DEF": "74",
        "STA": "110",
        "Legendary": "0",
        "CP_MAX": "942"
    },
    {
        "Name": "Beartic",
        "Pokedex_Number": "614",
        "Generation": "5",
        "Evolution_Stage": "Evolved",
        "Evolved": "0",
        "FamilyID": "",
        "type_1": "ice",
        "type_2": "",
        "weather_1": "Snow",
        "weather_2": "",
        "STAT_TOTAL": "575",
        "ATK": "233",
        "DEF": "152",
        "STA": "190",
        "Legendary": "0",
        "CP_MAX": "2865"
    },
    {
        "Name": "Cryogonal",
        "Pokedex_Number": "615",
        "Generation": "5",
        "Evolution_Stage": "Lower",
        "Evolved": "0",
        "FamilyID": "",
        "type_1": "ice",
        "type_2": "",
        "weather_1": "Snow",
        "weather_2": "",
        "STAT_TOTAL": "614",
        "ATK": "190",
        "DEF": "264",
        "STA": "160",
        "Legendary": "0",
        "CP_MAX": "2829"
    },
    {
        "Name": "Shelmet",
        "Pokedex_Number": "616",
        "Generation": "5",
        "Evolution_Stage": "",
        "Evolved": "0",
        "FamilyID": "",
        "type_1": "bug",
        "type_2": "",
        "weather_1": "Rainy",
        "weather_2": "",
        "STAT_TOTAL": "321",
        "ATK": "72",
        "DEF": "149",
        "STA": "100",
        "Legendary": "0",
        "CP_MAX": "746"
    },
    {
        "Name": "Accelgor",
        "Pokedex_Number": "617",
        "Generation": "5",
        "Evolution_Stage": "",
        "Evolved": "0",
        "FamilyID": "",
        "type_1": "bug",
        "type_2": "",
        "weather_1": "Rainy",
        "weather_2": "",
        "STAT_TOTAL": "511",
        "ATK": "220",
        "DEF": "131",
        "STA": "160",
        "Legendary": "0",
        "CP_MAX": "2346"
    },
    {
        "Name": "Stunfisk",
        "Pokedex_Number": "618",
        "Generation": "5",
        "Evolution_Stage": "Evolved",
        "Evolved": "0",
        "FamilyID": "",
        "type_1": "ground",
        "type_2": "electric",
        "weather_1": "Sunny/clear",
        "weather_2": "Rainy",
        "STAT_TOTAL": "539",
        "ATK": "144",
        "DEF": "177",
        "STA": "218",
        "Legendary": "0",
        "CP_MAX": "2100"
    },
    {
        "Name": "Mienfoo",
        "Pokedex_Number": "619",
        "Generation": "5",
        "Evolution_Stage": "",
        "Evolved": "0",
        "FamilyID": "",
        "type_1": "fighting",
        "type_2": "",
        "weather_1": "Cloudy",
        "weather_2": "",
        "STAT_TOTAL": "348",
        "ATK": "160",
        "DEF": "98",
        "STA": "90",
        "Legendary": "0",
        "CP_MAX": "1190"
    },
    {
        "Name": "Mienshao",
        "Pokedex_Number": "620",
        "Generation": "5",
        "Evolution_Stage": "",
        "Evolved": "0",
        "FamilyID": "",
        "type_1": "fighting",
        "type_2": "",
        "weather_1": "Cloudy",
        "weather_2": "",
        "STAT_TOTAL": "515",
        "ATK": "258",
        "DEF": "127",
        "STA": "130",
        "Legendary": "0",
        "CP_MAX": "2446"
    },
    {
        "Name": "Druddigon",
        "Pokedex_Number": "621",
        "Generation": "5",
        "Evolution_Stage": "Lower",
        "Evolved": "0",
        "FamilyID": "",
        "type_1": "dragon",
        "type_2": "",
        "weather_1": "Windy",
        "weather_2": "",
        "STAT_TOTAL": "537",
        "ATK": "213",
        "DEF": "170",
        "STA": "154",
        "Legendary": "0",
        "CP_MAX": "2517"
    },
    {
        "Name": "Golett",
        "Pokedex_Number": "622",
        "Generation": "5",
        "Evolution_Stage": "",
        "Evolved": "0",
        "FamilyID": "",
        "type_1": "ground",
        "type_2": "ghost",
        "weather_1": "Sunny/clear",
        "weather_2": "Fog",
        "STAT_TOTAL": "337",
        "ATK": "127",
        "DEF": "92",
        "STA": "118",
        "Legendary": "0",
        "CP_MAX": "1058"
    },
    {
        "Name": "Golurk",
        "Pokedex_Number": "623",
        "Generation": "5",
        "Evolution_Stage": "Lower",
        "Evolved": "0",
        "FamilyID": "",
        "type_1": "ground",
        "type_2": "ghost",
        "weather_1": "Sunny/clear",
        "weather_2": "Fog",
        "STAT_TOTAL": "554",
        "ATK": "222",
        "DEF": "154",
        "STA": "178",
        "Legendary": "0",
        "CP_MAX": "2673"
    },
    {
        "Name": "Pawniard",
        "Pokedex_Number": "624",
        "Generation": "5",
        "Evolution_Stage": "",
        "Evolved": "0",
        "FamilyID": "",
        "type_1": "dark",
        "type_2": "steel",
        "weather_1": "Fog",
        "weather_2": "Snow",
        "STAT_TOTAL": "373",
        "ATK": "154",
        "DEF": "129",
        "STA": "90",
        "Legendary": "0",
        "CP_MAX": "1297"
    },
    {
        "Name": "Bisharp",
        "Pokedex_Number": "625",
        "Generation": "5",
        "Evolution_Stage": "Evolved",
        "Evolved": "0",
        "FamilyID": "",
        "type_1": "dark",
        "type_2": "steel",
        "weather_1": "Fog",
        "weather_2": "Snow",
        "STAT_TOTAL": "553",
        "ATK": "232",
        "DEF": "191",
        "STA": "130",
        "Legendary": "0",
        "CP_MAX": "2666"
    },
    {
        "Name": "Bouffalant",
        "Pokedex_Number": "626",
        "Generation": "5",
        "Evolution_Stage": "Evolved",
        "Evolved": "0",
        "FamilyID": "",
        "type_1": "normal",
        "type_2": "",
        "weather_1": "Partly cloudy",
        "weather_2": "",
        "STAT_TOTAL": "567",
        "ATK": "195",
        "DEF": "182",
        "STA": "190",
        "Legendary": "0",
        "CP_MAX": "2635"
    },
    {
        "Name": "Rufflet",
        "Pokedex_Number": "627",
        "Generation": "5",
        "Evolution_Stage": "",
        "Evolved": "0",
        "FamilyID": "",
        "type_1": "normal",
        "type_2": "flying",
        "weather_1": "Partly cloudy",
        "weather_2": "Windy",
        "STAT_TOTAL": "387",
        "ATK": "150",
        "DEF": "97",
        "STA": "140",
        "Legendary": "0",
        "CP_MAX": "1357"
    },
    {
        "Name": "Braviary",
        "Pokedex_Number": "628",
        "Generation": "5",
        "Evolution_Stage": "Lower",
        "Evolved": "0",
        "FamilyID": "",
        "type_1": "normal",
        "type_2": "flying",
        "weather_1": "Partly cloudy",
        "weather_2": "Windy",
        "STAT_TOTAL": "584",
        "ATK": "232",
        "DEF": "152",
        "STA": "200",
        "Legendary": "0",
        "CP_MAX": "2923"
    },
    {
        "Name": "Vullaby",
        "Pokedex_Number": "629",
        "Generation": "5",
        "Evolution_Stage": "",
        "Evolved": "0",
        "FamilyID": "",
        "type_1": "dark",
        "type_2": "flying",
        "weather_1": "Fog",
        "weather_2": "Windy",
        "STAT_TOTAL": "389",
        "ATK": "105",
        "DEF": "144",
        "STA": "140",
        "Legendary": "0",
        "CP_MAX": "1176"
    },
    {
        "Name": "Mandibuzz",
        "Pokedex_Number": "630",
        "Generation": "5",
        "Evolution_Stage": "Evolved",
        "Evolved": "0",
        "FamilyID": "",
        "type_1": "dark",
        "type_2": "flying",
        "weather_1": "Fog",
        "weather_2": "Windy",
        "STAT_TOTAL": "559",
        "ATK": "129",
        "DEF": "210",
        "STA": "220",
        "Legendary": "0",
        "CP_MAX": "2068"
    },
    {
        "Name": "Heatmor",
        "Pokedex_Number": "631",
        "Generation": "5",
        "Evolution_Stage": "",
        "Evolved": "0",
        "FamilyID": "",
        "type_1": "fire",
        "type_2": "",
        "weather_1": "Sunny/clear",
        "weather_2": "",
        "STAT_TOTAL": "503",
        "ATK": "204",
        "DEF": "129",
        "STA": "170",
        "Legendary": "0",
        "CP_MAX": "2232"
    },
    {
        "Name": "Durant",
        "Pokedex_Number": "632",
        "Generation": "5",
        "Evolution_Stage": "Evolved",
        "Evolved": "0",
        "FamilyID": "",
        "type_1": "bug",
        "type_2": "steel",
        "weather_1": "Rainy",
        "weather_2": "Snow",
        "STAT_TOTAL": "555",
        "ATK": "217",
        "DEF": "222",
        "STA": "116",
        "Legendary": "0",
        "CP_MAX": "2553"
    },
    {
        "Name": "Deino",
        "Pokedex_Number": "633",
        "Generation": "5",
        "Evolution_Stage": "",
        "Evolved": "0",
        "FamilyID": "",
        "type_1": "dark",
        "type_2": "dragon",
        "weather_1": "Fog",
        "weather_2": "Windy",
        "STAT_TOTAL": "313",
        "ATK": "116",
        "DEF": "93",
        "STA": "104",
        "Legendary": "0",
        "CP_MAX": "927"
    },
    {
        "Name": "Zweilous",
        "Pokedex_Number": "634",
        "Generation": "5",
        "Evolution_Stage": "",
        "Evolved": "0",
        "FamilyID": "",
        "type_1": "dark",
        "type_2": "dragon",
        "weather_1": "Fog",
        "weather_2": "Windy",
        "STAT_TOTAL": "438",
        "ATK": "159",
        "DEF": "135",
        "STA": "144",
        "Legendary": "0",
        "CP_MAX": "1678"
    },
    {
        "Name": "Hydreigon",
        "Pokedex_Number": "635",
        "Generation": "5",
        "Evolution_Stage": "Lower",
        "Evolved": "0",
        "FamilyID": "",
        "type_1": "dark",
        "type_2": "dragon",
        "weather_1": "Fog",
        "weather_2": "Windy",
        "STAT_TOTAL": "628",
        "ATK": "256",
        "DEF": "188",
        "STA": "184",
        "Legendary": "0",
        "CP_MAX": "3401"
    }
]